grsched/__init__.py
grsched/__main__.py
grsched/__version__.py
grsched/_client.py
grsched/_config.py
grsched/_const.py
grsched/_event.py
grsched/_filter.py
grsched/_logger.py
grsched-0.0.2.dist-info/LICENSE
grsched-0.0.2.dist-info/METADATA
grsched-0.0.2.dist-info/WHEEL
grsched-0.0.2.dist-info/entry_points.txt
grsched-0.0.2.dist-info/top_level.txt
grsched-0.0.2.dist-info/RECORD
