Metadata-Version: 2.1
Name: grsched
Version: 0.0.2
Summary: DESCRIPTION
Home-page: https://github.com/thombashi/grsched
Author: Tsuyoshi Hombashi
Author-email: tsuyoshi.hombashi@gmail.com
License: MIT License
Project-URL: Documentation, https://grsched.rtfd.io/
Project-URL: Source, https://github.com/thombashi/grsched
Project-URL: Tracker, https://github.com/thombashi/grsched/issues
Platform: UNKNOWN
Classifier: Development Status :: 3 - Alpha
Classifier: Environment :: Console
Classifier: Intended Audience :: Information Technology
Classifier: License :: OSI Approved :: MIT License
Classifier: Operating System :: OS Independent
Classifier: Programming Language :: Python :: 3
Classifier: Programming Language :: Python :: 3.5
Classifier: Programming Language :: Python :: 3.6
Classifier: Programming Language :: Python :: 3.7
Classifier: Programming Language :: Python :: 3.8
Classifier: Programming Language :: Python :: 3.9
Classifier: Programming Language :: Python :: 3 :: Only
Classifier: Topic :: Terminals
Requires-Python: >=3.5
Requires-Dist: appconfigpy (<2,>=1.0.1)
Requires-Dist: click (<8,>=6.2)
Requires-Dist: DateTimeRange (<2,>=1.0.0)
Requires-Dist: envinfopy (<1,>=0.0.3)
Requires-Dist: loguru (<1,>=0.4.1)
Requires-Dist: pytablewriter (<1,>=0.58.0)
Requires-Dist: pytablewriter-altrow-theme (<1,>=0.0.2)
Requires-Dist: retryrequests (<1,>=0.0.2)
Requires-Dist: tcolorpy (<1,>=0.0.8)
Provides-Extra: test
Requires-Dist: pytest (>=6.0.1) ; extra == 'test'
Requires-Dist: pytest-md-report (>=0.1) ; extra == 'test'
Requires-Dist: subprocrunner (<2,>=1.2.1) ; extra == 'test'
